[
    {
        "added": "2013-06-04T22:16:13.340728",
        "annotation": "",
        "entry": "age",
        "id": 18028,
        "language": "/api/v1/language/edolo/",
        "loan": false,
        "resource_uri": "/api/v1/lexicon/18028/",
        "source": "/api/v1/source/shaw-1986/",
        "source_gloss": null,
        "word": "/api/v1/word/one/"
    },
    {
        "added": "2013-06-04T22:16:13.379353",
        "annotation": "",
        "entry": "agedu",
        "id": 18029,
        "language": "/api/v1/language/edolo/",
        "loan": false,
        "resource_uri": "/api/v1/lexicon/18029/",
        "source": "/api/v1/source/shaw-1986/",
        "source_gloss": null,
        "word": "/api/v1/word/two/"
    },
    {
        "added": "2013-06-04T22:16:12.715114",
        "annotation": "",
        "entry": "aube",
        "id": 17968,
        "language": "/api/v1/language/edolo/",
        "loan": false,
        "resource_uri": "/api/v1/lexicon/17968/",
        "source": "/api/v1/source/shaw-1986/",
        "source_gloss": null,
        "word": "/api/v1/word/moon/"
    },
    {
        "added": "2013-06-04T22:16:13.248479",
        "annotation": "",
        "entry": "augi\u028c",
        "id": 18020,
        "language": "/api/v1/language/edolo/",
        "loan": false,
        "resource_uri": "/api/v1/lexicon/18020/",
        "source": "/api/v1/source/shaw-1986/",
        "source_gloss": null,
        "word": "/api/v1/word/wing/"
    },
    {
        "added": "2013-06-04T22:16:12.954567",
        "annotation": "",
        "entry": "b\u223fp\u025bi",
        "id": 17995,
        "language": "/api/v1/language/edolo/",
        "loan": false,
        "resource_uri": "/api/v1/lexicon/17995/",
        "source": "/api/v1/source/shaw-1986/",
        "source_gloss": null,
        "word": "/api/v1/word/red/"
    },
    {
        "added": "2013-06-04T22:16:12.521509",
        "annotation": "",
        "entry": "b\u223fpus\u028c",
        "id": 17947,
        "language": "/api/v1/language/edolo/",
        "loan": false,
        "resource_uri": "/api/v1/lexicon/17947/",
        "source": "/api/v1/source/shaw-1986/",
        "source_gloss": null,
        "word": "/api/v1/word/head/"
    },
    {
        "added": "2013-06-04T22:16:12.530461",
        "annotation": "",
        "entry": "b\u223fpus\u028c heni",
        "id": 17948,
        "language": "/api/v1/language/edolo/",
        "loan": false,
        "resource_uri": "/api/v1/lexicon/17948/",
        "source": "/api/v1/source/shaw-1986/",
        "source_gloss": null,
        "word": "/api/v1/word/hair/"
    },
    {
        "added": "2013-06-04T22:16:12.924005",
        "annotation": "",
        "entry": "edef\u028cde",
        "id": 17991,
        "language": "/api/v1/language/edolo/",
        "loan": false,
        "resource_uri": "/api/v1/lexicon/17991/",
        "source": "/api/v1/source/shaw-1986/",
        "source_gloss": null,
        "word": "/api/v1/word/big/"
    },
    {
        "added": "2013-06-04T22:16:13.238143",
        "annotation": "",
        "entry": "\u1ebdi",
        "id": 18019,
        "language": "/api/v1/language/edolo/",
        "loan": false,
        "resource_uri": "/api/v1/lexicon/18019/",
        "source": "/api/v1/source/shaw-1986/",
        "source_gloss": null,
        "word": "/api/v1/word/name/"
    },
    {
        "added": "2013-06-04T22:16:12.590439",
        "annotation": "",
        "entry": "eli",
        "id": 17953,
        "language": "/api/v1/language/edolo/",
        "loan": false,
        "resource_uri": "/api/v1/lexicon/17953/",
        "source": "/api/v1/source/shaw-1986/",
        "source_gloss": null,
        "word": "/api/v1/word/tongue/"
    },
    {
        "added": "2013-06-04T22:16:12.633888",
        "annotation": "leg",
        "entry": "em\u0254",
        "id": 17959,
        "language": "/api/v1/language/edolo/",
        "loan": false,
        "resource_uri": "/api/v1/lexicon/17959/",
        "source": "/api/v1/source/shaw-1986/",
        "source_gloss": "leg",
        "word": "/api/v1/word/leg/"
    },
    {
        "added": "2013-06-04T22:16:12.640722",
        "annotation": "",
        "entry": "em\u0254gumu",
        "id": 17960,
        "language": "/api/v1/language/edolo/",
        "loan": false,
        "resource_uri": "/api/v1/lexicon/17960/",
        "source": "/api/v1/source/shaw-1986/",
        "source_gloss": null,
        "word": "/api/v1/word/knee/"
    },
    {
        "added": "2013-06-04T22:16:13.536458",
        "annotation": "",
        "entry": "esa",
        "id": 18040,
        "language": "/api/v1/language/edolo/",
        "loan": false,
        "resource_uri": "/api/v1/lexicon/18040/",
        "source": "/api/v1/source/shaw-1986/",
        "source_gloss": null,
        "word": "/api/v1/word/string-bag/"
    },
    {
        "added": "2013-06-04T22:16:12.703757",
        "annotation": "",
        "entry": "es\u0254",
        "id": 17967,
        "language": "/api/v1/language/edolo/",
        "loan": false,
        "resource_uri": "/api/v1/lexicon/17967/",
        "source": "/api/v1/source/shaw-1986/",
        "source_gloss": null,
        "word": "/api/v1/word/sun/"
    },
    {
        "added": "2013-06-04T22:16:13.260053",
        "annotation": "",
        "entry": "et\u0254",
        "id": 18021,
        "language": "/api/v1/language/edolo/",
        "loan": false,
        "resource_uri": "/api/v1/lexicon/18021/",
        "source": "/api/v1/source/shaw-1986/",
        "source_gloss": null,
        "word": "/api/v1/word/who/"
    },
    {
        "added": "2013-06-04T22:16:13.274616",
        "annotation": "",
        "entry": "et\u0254 suh\u00e3",
        "id": 18022,
        "language": "/api/v1/language/edolo/",
        "loan": false,
        "resource_uri": "/api/v1/lexicon/18022/",
        "source": "/api/v1/source/shaw-1986/",
        "source_gloss": null,
        "word": "/api/v1/word/what/"
    },
    {
        "added": "2013-06-04T22:16:12.961423",
        "annotation": "",
        "entry": "f\u028clei",
        "id": 17996,
        "language": "/api/v1/language/edolo/",
        "loan": false,
        "resource_uri": "/api/v1/lexicon/17996/",
        "source": "/api/v1/source/shaw-1986/",
        "source_gloss": null,
        "word": "/api/v1/word/white/"
    },
    {
        "added": "2013-06-04T22:16:13.404359",
        "annotation": "",
        "entry": "hab\u0254i",
        "id": 18032,
        "language": "/api/v1/language/edolo/",
        "loan": false,
        "resource_uri": "/api/v1/lexicon/18032/",
        "source": "/api/v1/source/shaw-1986/",
        "source_gloss": null,
        "word": "/api/v1/word/not/"
    },
    {
        "added": "2013-06-04T22:16:13.218444",
        "annotation": "flies",
        "entry": "hakila",
        "id": 18017,
        "language": "/api/v1/language/edolo/",
        "loan": false,
        "resource_uri": "/api/v1/lexicon/18017/",
        "source": "/api/v1/source/shaw-1986/",
        "source_gloss": "flies",
        "word": "/api/v1/word/to-fly/"
    },
    {
        "added": "2013-06-04T22:16:12.898508",
        "annotation": "",
        "entry": "hay\u028c",
        "id": 17987,
        "language": "/api/v1/language/edolo/",
        "loan": false,
        "resource_uri": "/api/v1/lexicon/17987/",
        "source": "/api/v1/source/shaw-1986/",
        "source_gloss": null,
        "word": "/api/v1/word/bird/"
    },
    {
        "added": "2013-06-04T22:16:12.938171",
        "annotation": "",
        "entry": "hedebi",
        "id": 17993,
        "language": "/api/v1/language/edolo/",
        "loan": false,
        "resource_uri": "/api/v1/lexicon/17993/",
        "source": "/api/v1/source/shaw-1986/",
        "source_gloss": null,
        "word": "/api/v1/word/good/"
    },
    {
        "added": "2013-06-04T22:16:12.989171",
        "annotation": "hot",
        "entry": "h\u1ebdig\u0129",
        "id": 18000,
        "language": "/api/v1/language/edolo/",
        "loan": false,
        "resource_uri": "/api/v1/lexicon/18000/",
        "source": "/api/v1/source/shaw-1986/",
        "source_gloss": "hot",
        "word": "/api/v1/word/hot/"
    },
    {
        "added": "2013-06-04T22:16:12.904400",
        "annotation": "",
        "entry": "he\u013e\u0129",
        "id": 17988,
        "language": "/api/v1/language/edolo/",
        "loan": false,
        "resource_uri": "/api/v1/lexicon/17988/",
        "source": "/api/v1/source/shaw-1986/",
        "source_gloss": null,
        "word": "/api/v1/word/feather/"
    },
    {
        "added": "2013-06-04T22:16:12.654684",
        "annotation": "",
        "entry": "hi\u028cle",
        "id": 17962,
        "language": "/api/v1/language/edolo/",
        "loan": false,
        "resource_uri": "/api/v1/lexicon/17962/",
        "source": "/api/v1/source/shaw-1986/",
        "source_gloss": null,
        "word": "/api/v1/word/blood/"
    },
    {
        "added": "2013-06-04T22:16:12.842715",
        "annotation": "",
        "entry": "h\u0254\u0303b\u00e3",
        "id": 17979,
        "language": "/api/v1/language/edolo/",
        "loan": false,
        "resource_uri": "/api/v1/lexicon/17979/",
        "source": "/api/v1/source/shaw-1986/",
        "source_gloss": null,
        "word": "/api/v1/word/smoke/"
    },
    {
        "added": "2013-06-04T22:16:12.892288",
        "annotation": "",
        "entry": "houpe",
        "id": 17986,
        "language": "/api/v1/language/edolo/",
        "loan": false,
        "resource_uri": "/api/v1/lexicon/17986/",
        "source": "/api/v1/source/shaw-1986/",
        "source_gloss": null,
        "word": "/api/v1/word/tail/"
    },
    {
        "added": "2013-06-04T22:16:13.472566",
        "annotation": "",
        "entry": "hu",
        "id": 18034,
        "language": "/api/v1/language/edolo/",
        "loan": false,
        "resource_uri": "/api/v1/lexicon/18034/",
        "source": "/api/v1/source/shaw-1986/",
        "source_gloss": null,
        "word": "/api/v1/word/meat/"
    },
    {
        "added": "2013-06-04T22:16:12.864657",
        "annotation": "",
        "entry": "i",
        "id": 17982,
        "language": "/api/v1/language/edolo/",
        "loan": false,
        "resource_uri": "/api/v1/lexicon/17982/",
        "source": "/api/v1/source/shaw-1986/",
        "source_gloss": null,
        "word": "/api/v1/word/tree/"
    },
    {
        "added": "2013-06-04T22:16:12.857844",
        "annotation": "path",
        "entry": "idi",
        "id": 17981,
        "language": "/api/v1/language/edolo/",
        "loan": false,
        "resource_uri": "/api/v1/lexicon/17981/",
        "source": "/api/v1/source/shaw-1986/",
        "source_gloss": "path",
        "word": "/api/v1/word/path/"
    },
    {
        "added": "2013-06-04T22:16:13.491313",
        "annotation": "",
        "entry": "ifi",
        "id": 18036,
        "language": "/api/v1/language/edolo/",
        "loan": false,
        "resource_uri": "/api/v1/lexicon/18036/",
        "source": "/api/v1/source/shaw-1986/",
        "source_gloss": null,
        "word": "/api/v1/word/claw/"
    },
    {
        "added": "2013-06-04T22:16:12.781530",
        "annotation": "",
        "entry": "igi",
        "id": 17975,
        "language": "/api/v1/language/edolo/",
        "loan": false,
        "resource_uri": "/api/v1/lexicon/17975/",
        "source": "/api/v1/source/shaw-1986/",
        "source_gloss": null,
        "word": "/api/v1/word/stone/"
    },
    {
        "added": "2013-06-04T22:16:13.514041",
        "annotation": "",
        "entry": "ik\u028cg\u028c",
        "id": 18038,
        "language": "/api/v1/language/edolo/",
        "loan": false,
        "resource_uri": "/api/v1/lexicon/18038/",
        "source": "/api/v1/source/shaw-1986/",
        "source_gloss": null,
        "word": "/api/v1/word/seed/"
    },
    {
        "added": "2013-06-04T22:16:13.328119",
        "annotation": "",
        "entry": "i k\u0254we",
        "id": 18027,
        "language": "/api/v1/language/edolo/",
        "loan": false,
        "resource_uri": "/api/v1/lexicon/18027/",
        "source": "/api/v1/source/shaw-1986/",
        "source_gloss": null,
        "word": "/api/v1/word/that/"
    },
    {
        "added": "2013-06-04T22:16:13.113932",
        "annotation": "",
        "entry": "im\u0254\u0303",
        "id": 18010,
        "language": "/api/v1/language/edolo/",
        "loan": false,
        "resource_uri": "/api/v1/lexicon/18010/",
        "source": "/api/v1/source/shaw-1986/",
        "source_gloss": null,
        "word": "/api/v1/word/to-give/"
    },
    {
        "added": "2013-06-04T22:16:13.297254",
        "annotation": "",
        "entry": "im\u0169",
        "id": 18024,
        "language": "/api/v1/language/edolo/",
        "loan": false,
        "resource_uri": "/api/v1/lexicon/18024/",
        "source": "/api/v1/source/shaw-1986/",
        "source_gloss": null,
        "word": "/api/v1/word/louse/"
    },
    {
        "added": "2013-06-04T22:16:13.411505",
        "annotation": "",
        "entry": "ipau",
        "id": 18033,
        "language": "/api/v1/language/edolo/",
        "loan": false,
        "resource_uri": "/api/v1/lexicon/18033/",
        "source": "/api/v1/source/shaw-1986/",
        "source_gloss": null,
        "word": "/api/v1/word/leaf/"
    },
    {
        "added": "2013-06-04T22:16:12.910478",
        "annotation": "",
        "entry": "is\u0254",
        "id": 17989,
        "language": "/api/v1/language/edolo/",
        "loan": false,
        "resource_uri": "/api/v1/lexicon/17989/",
        "source": "/api/v1/source/shaw-1986/",
        "source_gloss": null,
        "word": "/api/v1/word/egg/"
    },
    {
        "added": "2013-06-04T22:16:13.012803",
        "annotation": "",
        "entry": "kah\u1ebd",
        "id": 18003,
        "language": "/api/v1/language/edolo/",
        "loan": false,
        "resource_uri": "/api/v1/lexicon/18003/",
        "source": "/api/v1/source/shaw-1986/",
        "source_gloss": null,
        "word": "/api/v1/word/new/"
    },
    {
        "added": "2013-06-04T22:16:13.483432",
        "annotation": "",
        "entry": "kai",
        "id": 18035,
        "language": "/api/v1/language/edolo/",
        "loan": false,
        "resource_uri": "/api/v1/lexicon/18035/",
        "source": "/api/v1/source/shaw-1986/",
        "source_gloss": null,
        "word": "/api/v1/word/banana/"
    },
    {
        "added": "2013-06-04T22:16:12.597933",
        "annotation": "",
        "entry": "kal\u028cbag\u0254",
        "id": 17954,
        "language": "/api/v1/language/edolo/",
        "loan": false,
        "resource_uri": "/api/v1/lexicon/17954/",
        "source": "/api/v1/source/shaw-1986/",
        "source_gloss": null,
        "word": "/api/v1/word/neck/"
    },
    {
        "added": "2013-06-04T22:16:12.756312",
        "annotation": "",
        "entry": "kasigi",
        "id": 17972,
        "language": "/api/v1/language/edolo/",
        "loan": false,
        "resource_uri": "/api/v1/lexicon/17972/",
        "source": "/api/v1/source/shaw-1986/",
        "source_gloss": null,
        "word": "/api/v1/word/night/"
    },
    {
        "added": "2013-06-04T22:16:12.647619",
        "annotation": "",
        "entry": "k\u028cd\u0254f\u0254",
        "id": 17961,
        "language": "/api/v1/language/edolo/",
        "loan": false,
        "resource_uri": "/api/v1/lexicon/17961/",
        "source": "/api/v1/source/shaw-1986/",
        "source_gloss": null,
        "word": "/api/v1/word/skin/"
    },
    {
        "added": "2013-06-04T22:16:12.570248",
        "annotation": "",
        "entry": "k\u025bhe",
        "id": 17951,
        "language": "/api/v1/language/edolo/",
        "loan": false,
        "resource_uri": "/api/v1/lexicon/17951/",
        "source": "/api/v1/source/shaw-1986/",
        "source_gloss": null,
        "word": "/api/v1/word/ear/"
    },
    {
        "added": "2013-06-04T22:16:12.737480",
        "annotation": "",
        "entry": "kene",
        "id": 17970,
        "language": "/api/v1/language/edolo/",
        "loan": false,
        "resource_uri": "/api/v1/lexicon/17970/",
        "source": "/api/v1/source/shaw-1986/",
        "source_gloss": null,
        "word": "/api/v1/word/cloud/"
    },
    {
        "added": "2013-06-04T22:16:12.685498",
        "annotation": "",
        "entry": "kit\u00e3",
        "id": 17966,
        "language": "/api/v1/language/edolo/",
        "loan": false,
        "resource_uri": "/api/v1/lexicon/17966/",
        "source": "/api/v1/source/shaw-1986/",
        "source_gloss": null,
        "word": "/api/v1/word/shoulder/"
    },
    {
        "added": "2013-06-04T22:16:12.669622",
        "annotation": "",
        "entry": "kiwi:",
        "id": 17964,
        "language": "/api/v1/language/edolo/",
        "loan": false,
        "resource_uri": "/api/v1/lexicon/17964/",
        "source": "/api/v1/source/shaw-1986/",
        "source_gloss": null,
        "word": "/api/v1/word/bone/"
    },
    {
        "added": "2013-06-04T22:16:12.878460",
        "annotation": "",
        "entry": "k\u0254f\u0254t\u0254\u0303",
        "id": 17984,
        "language": "/api/v1/language/edolo/",
        "loan": false,
        "resource_uri": "/api/v1/lexicon/17984/",
        "source": "/api/v1/source/shaw-1986/",
        "source_gloss": null,
        "word": "/api/v1/word/bark/"
    },
    {
        "added": "2013-06-04T22:16:12.996121",
        "annotation": "",
        "entry": "k\u0254g\u0129",
        "id": 18001,
        "language": "/api/v1/language/edolo/",
        "loan": false,
        "resource_uri": "/api/v1/lexicon/18001/",
        "source": "/api/v1/source/shaw-1986/",
        "source_gloss": null,
        "word": "/api/v1/word/cold/"
    },
    {
        "added": "2013-06-04T22:16:13.317215",
        "annotation": "",
        "entry": "k\u0254we",
        "id": 18026,
        "language": "/api/v1/language/edolo/",
        "loan": false,
        "resource_uri": "/api/v1/lexicon/18026/",
        "source": "/api/v1/source/shaw-1986/",
        "source_gloss": null,
        "word": "/api/v1/word/this/"
    },
    {
        "added": "2013-06-04T22:16:13.208096",
        "annotation": "",
        "entry": "ma:sipe",
        "id": 18016,
        "language": "/api/v1/language/edolo/",
        "loan": false,
        "resource_uri": "/api/v1/lexicon/18016/",
        "source": "/api/v1/source/shaw-1986/",
        "source_gloss": null,
        "word": "/api/v1/word/to-come/"
    },
    {
        "added": "2013-06-04T22:16:12.982193",
        "annotation": "",
        "entry": "m\u1ebdlabui",
        "id": 17999,
        "language": "/api/v1/language/edolo/",
        "loan": false,
        "resource_uri": "/api/v1/lexicon/17999/",
        "source": "/api/v1/source/shaw-1986/",
        "source_gloss": null,
        "word": "/api/v1/word/green/"
    },
    {
        "added": "2013-06-04T22:16:12.559431",
        "annotation": "",
        "entry": "mig\u028cni",
        "id": 17950,
        "language": "/api/v1/language/edolo/",
        "loan": false,
        "resource_uri": "/api/v1/lexicon/17950/",
        "source": "/api/v1/source/shaw-1986/",
        "source_gloss": null,
        "word": "/api/v1/word/nose/"
    },
    {
        "added": "2013-06-04T22:16:13.228085",
        "annotation": "",
        "entry": "mih\u0269\u0303sip\u025b\u0303",
        "id": 18018,
        "language": "/api/v1/language/edolo/",
        "loan": false,
        "resource_uri": "/api/v1/lexicon/18018/",
        "source": "/api/v1/source/shaw-1986/",
        "source_gloss": null,
        "word": "/api/v1/word/to-bite/"
    },
    {
        "added": "2013-06-04T22:16:13.161543",
        "annotation": "",
        "entry": "miti\u025b\u0303",
        "id": 18012,
        "language": "/api/v1/language/edolo/",
        "loan": false,
        "resource_uri": "/api/v1/lexicon/18012/",
        "source": "/api/v1/source/shaw-1986/",
        "source_gloss": null,
        "word": "/api/v1/word/to-lie-down/"
    },
    {
        "added": "2013-06-04T22:16:13.085441",
        "annotation": "",
        "entry": "miy\u1ebd",
        "id": 18007,
        "language": "/api/v1/language/edolo/",
        "loan": false,
        "resource_uri": "/api/v1/lexicon/18007/",
        "source": "/api/v1/source/shaw-1986/",
        "source_gloss": null,
        "word": "/api/v1/word/to-sit/"
    },
    {
        "added": "2013-06-04T22:16:13.104282",
        "annotation": "",
        "entry": "m\u0254s\u0254\u0303",
        "id": 18009,
        "language": "/api/v1/language/edolo/",
        "loan": false,
        "resource_uri": "/api/v1/lexicon/18009/",
        "source": "/api/v1/source/shaw-1986/",
        "source_gloss": null,
        "word": "/api/v1/word/to-walk/"
    },
    {
        "added": "2013-06-04T22:16:13.184980",
        "annotation": "",
        "entry": "nab\u028cba",
        "id": 18014,
        "language": "/api/v1/language/edolo/",
        "loan": false,
        "resource_uri": "/api/v1/lexicon/18014/",
        "source": "/api/v1/source/shaw-1986/",
        "source_gloss": null,
        "word": "/api/v1/word/to-hear/"
    },
    {
        "added": "2013-06-04T22:16:12.606155",
        "annotation": "",
        "entry": "nafi",
        "id": 17955,
        "language": "/api/v1/language/edolo/",
        "loan": false,
        "resource_uri": "/api/v1/lexicon/17955/",
        "source": "/api/v1/source/shaw-1986/",
        "source_gloss": null,
        "word": "/api/v1/word/mouth/"
    },
    {
        "added": "2013-06-04T22:16:13.021193",
        "annotation": "",
        "entry": "nah\u00e3:",
        "id": 18004,
        "language": "/api/v1/language/edolo/",
        "loan": false,
        "resource_uri": "/api/v1/lexicon/18004/",
        "source": "/api/v1/source/shaw-1986/",
        "source_gloss": null,
        "word": "/api/v1/word/to-eat/"
    },
    {
        "added": "2013-06-04T22:16:12.775544",
        "annotation": "",
        "entry": "naka",
        "id": 17974,
        "language": "/api/v1/language/edolo/",
        "loan": false,
        "resource_uri": "/api/v1/lexicon/17974/",
        "source": "/api/v1/source/shaw-1986/",
        "source_gloss": null,
        "word": "/api/v1/word/ground/"
    },
    {
        "added": "2013-06-04T22:16:12.613575",
        "annotation": "arm",
        "entry": "n\u028cb\u0254",
        "id": 17956,
        "language": "/api/v1/language/edolo/",
        "loan": false,
        "resource_uri": "/api/v1/lexicon/17956/",
        "source": "/api/v1/source/shaw-1986/",
        "source_gloss": "arm",
        "word": "/api/v1/word/arm/"
    },
    {
        "added": "2013-06-04T22:16:12.443578",
        "annotation": "",
        "entry": "ne",
        "id": 17943,
        "language": "/api/v1/language/edolo/",
        "loan": false,
        "resource_uri": "/api/v1/lexicon/17943/",
        "source": "/api/v1/source/shaw-1986/",
        "source_gloss": null,
        "word": "/api/v1/word/i/"
    },
    {
        "added": "2013-06-04T22:16:12.930574",
        "annotation": "",
        "entry": "n\u025b\u0303f\u028cni",
        "id": 17992,
        "language": "/api/v1/language/edolo/",
        "loan": false,
        "resource_uri": "/api/v1/lexicon/17992/",
        "source": "/api/v1/source/shaw-1986/",
        "source_gloss": null,
        "word": "/api/v1/word/small/"
    },
    {
        "added": "2013-06-04T22:16:13.524874",
        "annotation": "",
        "entry": "n\u025bme",
        "id": 18039,
        "language": "/api/v1/language/edolo/",
        "loan": false,
        "resource_uri": "/api/v1/lexicon/18039/",
        "source": "/api/v1/source/shaw-1986/",
        "source_gloss": null,
        "word": "/api/v1/word/mother/"
    },
    {
        "added": "2013-06-04T22:16:12.460857",
        "annotation": "",
        "entry": "nini",
        "id": 17945,
        "language": "/api/v1/language/edolo/",
        "loan": false,
        "resource_uri": "/api/v1/lexicon/17945/",
        "source": "/api/v1/source/shaw-1986/",
        "source_gloss": null,
        "word": "/api/v1/word/we/"
    },
    {
        "added": "2013-06-04T22:16:12.850088",
        "annotation": "",
        "entry": "nisipu",
        "id": 17980,
        "language": "/api/v1/language/edolo/",
        "loan": false,
        "resource_uri": "/api/v1/lexicon/17980/",
        "source": "/api/v1/source/shaw-1986/",
        "source_gloss": null,
        "word": "/api/v1/word/ashes/"
    },
    {
        "added": "2013-06-04T22:16:13.075900",
        "annotation": "",
        "entry": "n\u0254wem\u0254",
        "id": 18006,
        "language": "/api/v1/language/edolo/",
        "loan": false,
        "resource_uri": "/api/v1/lexicon/18006/",
        "source": "/api/v1/source/shaw-1986/",
        "source_gloss": null,
        "word": "/api/v1/word/to-stand/"
    },
    {
        "added": "2013-06-04T22:16:13.502457",
        "annotation": "",
        "entry": "n\u028ct\u0254",
        "id": 18037,
        "language": "/api/v1/language/edolo/",
        "loan": false,
        "resource_uri": "/api/v1/lexicon/18037/",
        "source": "/api/v1/source/shaw-1986/",
        "source_gloss": null,
        "word": "/api/v1/word/father/"
    },
    {
        "added": "2013-06-04T22:16:12.817299",
        "annotation": "",
        "entry": "nulu",
        "id": 17978,
        "language": "/api/v1/language/edolo/",
        "loan": false,
        "resource_uri": "/api/v1/lexicon/17978/",
        "source": "/api/v1/source/shaw-1986/",
        "source_gloss": null,
        "word": "/api/v1/word/fire/"
    },
    {
        "added": "2013-06-04T22:16:13.286180",
        "annotation": "",
        "entry": "nuluku\u028c",
        "id": 18023,
        "language": "/api/v1/language/edolo/",
        "loan": false,
        "resource_uri": "/api/v1/lexicon/18023/",
        "source": "/api/v1/source/shaw-1986/",
        "source_gloss": null,
        "word": "/api/v1/word/to-burn/"
    },
    {
        "added": "2013-06-04T22:16:12.884834",
        "annotation": "",
        "entry": "\u0254g\u0254n\u0254",
        "id": 17985,
        "language": "/api/v1/language/edolo/",
        "loan": false,
        "resource_uri": "/api/v1/lexicon/17985/",
        "source": "/api/v1/source/shaw-1986/",
        "source_gloss": null,
        "word": "/api/v1/word/dog/"
    },
    {
        "added": "2013-06-04T22:16:12.766151",
        "annotation": "",
        "entry": "\u0254\u0303t\u00e3",
        "id": 17973,
        "language": "/api/v1/language/edolo/",
        "loan": false,
        "resource_uri": "/api/v1/lexicon/17973/",
        "source": "/api/v1/source/shaw-1986/",
        "source_gloss": null,
        "word": "/api/v1/word/water/"
    },
    {
        "added": "2013-06-04T22:16:12.678124",
        "annotation": "",
        "entry": "pagi",
        "id": 17965,
        "language": "/api/v1/language/edolo/",
        "loan": false,
        "resource_uri": "/api/v1/lexicon/17965/",
        "source": "/api/v1/source/shaw-1986/",
        "source_gloss": null,
        "word": "/api/v1/word/back/"
    },
    {
        "added": "2013-06-04T22:16:13.395417",
        "annotation": "kills",
        "entry": "pak\u0254wi",
        "id": 18031,
        "language": "/api/v1/language/edolo/",
        "loan": false,
        "resource_uri": "/api/v1/lexicon/18031/",
        "source": "/api/v1/source/shaw-1986/",
        "source_gloss": "kills",
        "word": "/api/v1/word/to-kill/"
    },
    {
        "added": "2013-06-04T22:16:12.580379",
        "annotation": "",
        "entry": "p\u223fbese",
        "id": 17952,
        "language": "/api/v1/language/edolo/",
        "loan": false,
        "resource_uri": "/api/v1/lexicon/17952/",
        "source": "/api/v1/source/shaw-1986/",
        "source_gloss": null,
        "word": "/api/v1/word/tooth/"
    },
    {
        "added": "2013-06-04T22:16:13.172890",
        "annotation": "",
        "entry": "peyaha",
        "id": 18013,
        "language": "/api/v1/language/edolo/",
        "loan": false,
        "resource_uri": "/api/v1/lexicon/18013/",
        "source": "/api/v1/source/shaw-1986/",
        "source_gloss": null,
        "word": "/api/v1/word/to-see/"
    },
    {
        "added": "2013-06-04T22:16:12.626808",
        "annotation": "",
        "entry": "p\u0254l\u025b",
        "id": 17958,
        "language": "/api/v1/language/edolo/",
        "loan": false,
        "resource_uri": "/api/v1/lexicon/17958/",
        "source": "/api/v1/source/shaw-1986/",
        "source_gloss": null,
        "word": "/api/v1/word/belly/"
    },
    {
        "added": "2013-06-04T22:16:12.662479",
        "annotation": "fat",
        "entry": "s\u00e3f\u1ebd",
        "id": 17963,
        "language": "/api/v1/language/edolo/",
        "loan": false,
        "resource_uri": "/api/v1/lexicon/17963/",
        "source": "/api/v1/source/shaw-1986/",
        "source_gloss": "fat",
        "word": "/api/v1/word/fat/"
    },
    {
        "added": "2013-06-04T22:16:13.095034",
        "annotation": "",
        "entry": "s\u00e3sibe",
        "id": 18008,
        "language": "/api/v1/language/edolo/",
        "loan": false,
        "resource_uri": "/api/v1/lexicon/18008/",
        "source": "/api/v1/source/shaw-1986/",
        "source_gloss": null,
        "word": "/api/v1/word/to-speak/"
    },
    {
        "added": "2013-06-04T22:16:12.946767",
        "annotation": "",
        "entry": "sedade",
        "id": 17994,
        "language": "/api/v1/language/edolo/",
        "loan": false,
        "resource_uri": "/api/v1/lexicon/17994/",
        "source": "/api/v1/source/shaw-1986/",
        "source_gloss": null,
        "word": "/api/v1/word/long/"
    },
    {
        "added": "2013-06-04T22:16:12.745514",
        "annotation": "rain",
        "entry": "sege",
        "id": 17971,
        "language": "/api/v1/language/edolo/",
        "loan": false,
        "resource_uri": "/api/v1/lexicon/17971/",
        "source": "/api/v1/source/shaw-1986/",
        "source_gloss": "rain",
        "word": "/api/v1/word/rain/"
    },
    {
        "added": "2013-06-04T22:16:12.794382",
        "annotation": "",
        "entry": "segebi",
        "id": 17977,
        "language": "/api/v1/language/edolo/",
        "loan": false,
        "resource_uri": "/api/v1/lexicon/17977/",
        "source": "/api/v1/source/shaw-1986/",
        "source_gloss": null,
        "word": "/api/v1/word/mountain/"
    },
    {
        "added": "2013-06-04T22:16:12.916552",
        "annotation": "",
        "entry": "seme",
        "id": 17990,
        "language": "/api/v1/language/edolo/",
        "loan": false,
        "resource_uri": "/api/v1/lexicon/17990/",
        "source": "/api/v1/source/shaw-1986/",
        "source_gloss": null,
        "word": "/api/v1/word/fish/"
    },
    {
        "added": "2013-06-04T22:16:12.538169",
        "annotation": "",
        "entry": "si",
        "id": 17949,
        "language": "/api/v1/language/edolo/",
        "loan": false,
        "resource_uri": "/api/v1/lexicon/17949/",
        "source": "/api/v1/source/shaw-1986/",
        "source_gloss": null,
        "word": "/api/v1/word/eye/"
    },
    {
        "added": "2013-06-04T22:16:12.727592",
        "annotation": "",
        "entry": "sikabi",
        "id": 17969,
        "language": "/api/v1/language/edolo/",
        "loan": false,
        "resource_uri": "/api/v1/lexicon/17969/",
        "source": "/api/v1/source/shaw-1986/",
        "source_gloss": null,
        "word": "/api/v1/word/star/"
    },
    {
        "added": "2013-06-04T22:16:12.787489",
        "annotation": "",
        "entry": "sugu\u028c",
        "id": 17976,
        "language": "/api/v1/language/edolo/",
        "loan": false,
        "resource_uri": "/api/v1/lexicon/17976/",
        "source": "/api/v1/source/shaw-1986/",
        "source_gloss": null,
        "word": "/api/v1/word/pig/"
    },
    {
        "added": "2013-06-04T22:16:12.469820",
        "annotation": "",
        "entry": "susubat\u0254",
        "id": 17946,
        "language": "/api/v1/language/edolo/",
        "loan": false,
        "resource_uri": "/api/v1/lexicon/17946/",
        "source": "/api/v1/source/shaw-1986/",
        "source_gloss": null,
        "word": "/api/v1/word/all/"
    },
    {
        "added": "2013-06-04T22:16:13.196477",
        "annotation": "",
        "entry": "tadisigai",
        "id": 18015,
        "language": "/api/v1/language/edolo/",
        "loan": false,
        "resource_uri": "/api/v1/lexicon/18015/",
        "source": "/api/v1/source/shaw-1986/",
        "source_gloss": null,
        "word": "/api/v1/word/to-swim/"
    },
    {
        "added": "2013-06-04T22:16:13.388308",
        "annotation": "",
        "entry": "tawa",
        "id": 18030,
        "language": "/api/v1/language/edolo/",
        "loan": false,
        "resource_uri": "/api/v1/lexicon/18030/",
        "source": "/api/v1/source/shaw-1986/",
        "source_gloss": null,
        "word": "/api/v1/word/to-know/"
    },
    {
        "added": "2013-06-04T22:16:12.452858",
        "annotation": "you",
        "entry": "ti:",
        "id": 17944,
        "language": "/api/v1/language/edolo/",
        "loan": false,
        "resource_uri": "/api/v1/lexicon/17944/",
        "source": "/api/v1/source/shaw-1986/",
        "source_gloss": "you",
        "word": "/api/v1/word/you/"
    },
    {
        "added": "2013-06-04T22:16:12.872089",
        "annotation": "",
        "entry": "tifi",
        "id": 17983,
        "language": "/api/v1/language/edolo/",
        "loan": false,
        "resource_uri": "/api/v1/lexicon/17983/",
        "source": "/api/v1/source/shaw-1986/",
        "source_gloss": null,
        "word": "/api/v1/word/root/"
    },
    {
        "added": "2013-06-04T22:16:13.135244",
        "annotation": "",
        "entry": "ti\u028ch\u00e3",
        "id": 18011,
        "language": "/api/v1/language/edolo/",
        "loan": false,
        "resource_uri": "/api/v1/lexicon/18011/",
        "source": "/api/v1/source/shaw-1986/",
        "source_gloss": null,
        "word": "/api/v1/word/to-sleep/"
    },
    {
        "added": "2013-06-04T22:16:11.538380",
        "annotation": "",
        "entry": "t\u0254n\u0254",
        "id": 17941,
        "language": "/api/v1/language/edolo/",
        "loan": false,
        "resource_uri": "/api/v1/lexicon/17941/",
        "source": "/api/v1/source/shaw-1986/",
        "source_gloss": null,
        "word": "/api/v1/word/man/"
    },
    {
        "added": "2013-06-04T22:16:12.620238",
        "annotation": "",
        "entry": "t\u0254t\u0254",
        "id": 17957,
        "language": "/api/v1/language/edolo/",
        "loan": false,
        "resource_uri": "/api/v1/lexicon/17957/",
        "source": "/api/v1/source/shaw-1986/",
        "source_gloss": null,
        "word": "/api/v1/word/breast/"
    },
    {
        "added": "2013-06-04T22:16:12.326224",
        "annotation": "",
        "entry": "udia",
        "id": 17942,
        "language": "/api/v1/language/edolo/",
        "loan": false,
        "resource_uri": "/api/v1/lexicon/17942/",
        "source": "/api/v1/source/shaw-1986/",
        "source_gloss": null,
        "word": "/api/v1/word/woman/"
    },
    {
        "added": "2013-06-04T22:16:13.003881",
        "annotation": "",
        "entry": "w\u00e3l\u00e3sube",
        "id": 18002,
        "language": "/api/v1/language/edolo/",
        "loan": false,
        "resource_uri": "/api/v1/lexicon/18002/",
        "source": "/api/v1/source/shaw-1986/",
        "source_gloss": null,
        "word": "/api/v1/word/full/"
    },
    {
        "added": "2013-06-04T22:16:13.027854",
        "annotation": "",
        "entry": "wid\u028c",
        "id": 18005,
        "language": "/api/v1/language/edolo/",
        "loan": false,
        "resource_uri": "/api/v1/lexicon/18005/",
        "source": "/api/v1/source/shaw-1986/",
        "source_gloss": null,
        "word": "/api/v1/word/cassowary/"
    },
    {
        "added": "2013-06-04T22:16:12.975022",
        "annotation": "",
        "entry": "w\u028cn\u0254i",
        "id": 17998,
        "language": "/api/v1/language/edolo/",
        "loan": false,
        "resource_uri": "/api/v1/lexicon/17998/",
        "source": "/api/v1/source/shaw-1986/",
        "source_gloss": null,
        "word": "/api/v1/word/yellow/"
    },
    {
        "added": "2013-06-04T22:16:12.968303",
        "annotation": "",
        "entry": "y\u028cbui",
        "id": 17997,
        "language": "/api/v1/language/edolo/",
        "loan": false,
        "resource_uri": "/api/v1/lexicon/17997/",
        "source": "/api/v1/source/shaw-1986/",
        "source_gloss": null,
        "word": "/api/v1/word/black/"
    },
    {
        "added": "2013-06-04T22:16:13.307349",
        "annotation": "",
        "entry": "y\u028cfi\u025b",
        "id": 18025,
        "language": "/api/v1/language/edolo/",
        "loan": false,
        "resource_uri": "/api/v1/lexicon/18025/",
        "source": "/api/v1/source/shaw-1986/",
        "source_gloss": null,
        "word": "/api/v1/word/many/"
    }
]